dgps/__init__.py
dgps/firestore/FirestoreAdministrator.py
dgps/firestore/__init__.py
dgps/utils/__init__.py
dgps_firestore-0.1.7.dist-info/METADATA
dgps_firestore-0.1.7.dist-info/WHEEL
dgps_firestore-0.1.7.dist-info/top_level.txt
dgps_firestore-0.1.7.dist-info/RECORD
