Metadata-Version: 2.1
Name: dgps-firestore
Version: 0.1.7
Summary: Utility functions for DemocracyGPS
Home-page: https://www.democracygps.org/team
Author: Chris Krenn
Author-email: crkrenn@gmail.com
License: UNKNOWN
Platform: UNKNOWN
Requires-Dist: pytz
Requires-Dist: google-cloud-firestore
